Metadata-Version: 2.4
Name: mcp-document-brain-circlci
Version: 0.1.3
Summary: MCP server for converting files to markdown using Markitdown
Author-email: Armstrong Asenavi <zattufinancialanlyst@gmail.com>
License: MIT
Classifier: Programming Language :: Python :: 3
Classifier: License :: OSI Approved :: MIT License
Classifier: Operating System :: OS Independent
Requires-Python: >=3.12
Requires-Dist: mcp[cli]>=1.8.0
Requires-Dist: markitdown[all]>=0.1.1
Provides-Extra: dev
Requires-Dist: build>=1.2.2.post1; extra == "dev"
Requires-Dist: pytest>=8.3.5; extra == "dev"
Requires-Dist: twine>=6.1.0; extra == "dev"
